{
  "project_info": {
    "project_number": "154794588260",
    "project_id": "chhotya-jahirati",
    "storage_bucket": "chhotya-jahirati.appspot.com"
  },
  "client": [
    {
      "client_info": {
        "mobilesdk_app_id": "1:154794588260:android:9406aa04739334d679c771",
        "android_client_info": {
          "package_name": "com.kimotest"
        }
      },
      "oauth_client": [],
      "api_key": [
        {
          "current_key": "AIzaSyCjwq5rhutV6gggjHsFEwG7qH3JIkciR3o"
        }
      ],
      "services": {
        "appinvite_service": {
          "other_platform_oauth_client": []
        }
      }
    }
  ],
  "configuration_version": "1"
}